README.md
setup.py
kline_redis/__init__.py
kline_redis/api.py
kline_redis/binance_kline.py
kline_redis/cli.py
kline_redis/kline_redis.py
kline_redis/repair.py
kline_redis/util.py
kline_redis.egg-info/PKG-INFO
kline_redis.egg-info/SOURCES.txt
kline_redis.egg-info/dependency_links.txt
kline_redis.egg-info/entry_points.txt
kline_redis.egg-info/requires.txt
kline_redis.egg-info/top_level.txt