Metadata-Version: 2.1
Name: kline-redis
Version: 0.1.3
Summary: K 线数据 redisk 缓存
License: UNKNOWN
Platform: UNKNOWN
